bp/__about__.py
bp/__init__.py
bp/handle.py
bp/jobs.py
bp/utility.py
pybp-0.0.2.dist-info/METADATA
pybp-0.0.2.dist-info/WHEEL
pybp-0.0.2.dist-info/licenses/LICENSE
pybp-0.0.2.dist-info/RECORD
